{
 "_NetworKit":{
  "__set__":true,
  "elements":[
   "networkit-5.0-py36h6de7cb9_0",
   "networkit-5.0-py36he1b5a44_0",
   "networkit-5.0-py37h6de7cb9_0",
   "networkit-5.0-py37he1b5a44_0",
   "networkit-5.0.1-py36h6de7cb9_0",
   "networkit-5.0.1-py36he1b5a44_0",
   "networkit-5.0.1-py37h6de7cb9_0",
   "networkit-5.0.1-py37he1b5a44_0",
   "networkit-6.0-py36h48182ed_0",
   "networkit-6.0-py36h48182ed_1",
   "networkit-6.0-py36h4f17bb1_1",
   "networkit-6.0-py36hb3f55d8_1",
   "networkit-6.0-py36hc13618b_0",
   "networkit-6.0-py36hc13618b_1",
   "networkit-6.0-py37h48182ed_0",
   "networkit-6.0-py37h48182ed_1",
   "networkit-6.0-py37h4f17bb1_1",
   "networkit-6.0-py37hb3f55d8_1",
   "networkit-6.0-py37hc13618b_0",
   "networkit-6.0-py37hc13618b_1",
   "networkit-6.0-py38h4f17bb1_1",
   "networkit-6.0-py38hb3f55d8_1",
   "networkit-6.1-py36h4f17bb1_0",
   "networkit-6.1-py36h4f17bb1_1",
   "networkit-6.1-py36h830a2c2_2",
   "networkit-6.1-py36h830a2c2_3",
   "networkit-6.1-py36h830a2c2_4",
   "networkit-6.1-py36hb3f55d8_0",
   "networkit-6.1-py36hb3f55d8_1",
   "networkit-6.1-py36hcc1bba6_2",
   "networkit-6.1-py36hcc1bba6_4",
   "networkit-6.1-py37h0da4684_2",
   "networkit-6.1-py37h0da4684_3",
   "networkit-6.1-py37h0da4684_4",
   "networkit-6.1-py37h4f17bb1_0",
   "networkit-6.1-py37h4f17bb1_1",
   "networkit-6.1-py37h94625e5_2",
   "networkit-6.1-py37h94625e5_4",
   "networkit-6.1-py37hb3f55d8_0",
   "networkit-6.1-py37hb3f55d8_1",
   "networkit-6.1-py38h4f17bb1_0",
   "networkit-6.1-py38h4f17bb1_1",
   "networkit-6.1-py38h5fc983b_2",
   "networkit-6.1-py38h5fc983b_4",
   "networkit-6.1-py38hb3f55d8_0",
   "networkit-6.1-py38hb3f55d8_1",
   "networkit-6.1-py38hcb8c335_2",
   "networkit-6.1-py38hcb8c335_3",
   "networkit-6.1-py38hcb8c335_4",
   "networkit-7.0-py36h830a2c2_0",
   "networkit-7.0-py36hcc1bba6_0",
   "networkit-7.0-py37h0da4684_0",
   "networkit-7.0-py37h94625e5_0",
   "networkit-7.0-py38h5fc983b_0",
   "networkit-7.0-py38hcb8c335_0"
  ]
 },
 "_nds2":{
  "__set__":true,
  "elements":[
   "python-nds2-client-0.16.7-py36hd7f5668_1",
   "python-nds2-client-0.16.7-py37h414f9d2_1",
   "python-nds2-client-0.16.7-py38h251f6bf_1",
   "python-nds2-client-0.16.8-py36hd7f5668_0",
   "python-nds2-client-0.16.8-py36hd7f5668_1",
   "python-nds2-client-0.16.8-py37h414f9d2_0",
   "python-nds2-client-0.16.8-py37h414f9d2_1",
   "python-nds2-client-0.16.8-py38h251f6bf_0",
   "python-nds2-client-0.16.8-py38h251f6bf_1",
   "python-nds2-client-0.16.8-py39h6ab05e5_1"
  ]
 },
 "_nlopt":{
  "__set__":true,
  "elements":[
   "nlopt-2.4.2-py27_vc9_1",
   "nlopt-2.4.2-py27_vc9_2",
   "nlopt-2.4.2-py27h39f3610_3",
   "nlopt-2.4.2-py34_vc10_1",
   "nlopt-2.4.2-py35_vc14_1",
   "nlopt-2.4.2-py35_vc14_2",
   "nlopt-2.4.2-py35h830ac7b_3",
   "nlopt-2.4.2-py36_vc14_1",
   "nlopt-2.4.2-py36_vc14_2",
   "nlopt-2.4.2-py36h830ac7b_3",
   "nlopt-2.5.0-py27h0b75458_1000",
   "nlopt-2.5.0-py27h39f3610_0",
   "nlopt-2.5.0-py35h830ac7b_0",
   "nlopt-2.5.0-py36h830ac7b_0",
   "nlopt-2.5.0-py36hfafe4ec_1000",
   "nlopt-2.5.0-py37hfafe4ec_1000",
   "nlopt-2.6.0-py27h0b75458_0",
   "nlopt-2.6.0-py36hfafe4ec_0",
   "nlopt-2.6.0-py37hfafe4ec_0",
   "nlopt-2.6.1-py27h0b75458_0",
   "nlopt-2.6.1-py27h0b75458_1",
   "nlopt-2.6.1-py27h4ded528_1",
   "nlopt-2.6.1-py36h69e1c5c_1",
   "nlopt-2.6.1-py36h8f2c165_2",
   "nlopt-2.6.1-py36hfafe4ec_0",
   "nlopt-2.6.1-py36hfafe4ec_1",
   "nlopt-2.6.1-py37h69e1c5c_1",
   "nlopt-2.6.1-py37hf92ba0c_2",
   "nlopt-2.6.1-py37hfafe4ec_0",
   "nlopt-2.6.1-py37hfafe4ec_1",
   "nlopt-2.6.1-py38h69e1c5c_1",
   "nlopt-2.6.1-py38ha735ab1_2",
   "nlopt-2.6.2-py36hb8e8622_1",
   "nlopt-2.6.2-py36hc6fae17_0",
   "nlopt-2.6.2-py37h076b467_1",
   "nlopt-2.6.2-py37h62b1fd7_0",
   "nlopt-2.6.2-py38h3ae069c_1",
   "nlopt-2.6.2-py38hc8157d0_0",
   "nlopt-2.6.2-py39h86cf8cf_1",
   "nlopt-2.7.0-py36hbe29271_0",
   "nlopt-2.7.0-py37ha363f11_0",
   "nlopt-2.7.0-py38h7b55a0d_0",
   "nlopt-2.7.0-py39hc0c4d14_0"
  ]
 },
 "_nmtlib":{
  "__set__":true,
  "elements":[
   "namaster-0.9-py36h3b4356e_0",
   "namaster-0.9-py36h80e476a_0",
   "namaster-0.9-py36h80e476a_1",
   "namaster-0.9-py36h94a39f0_1000",
   "namaster-0.9-py36h94a39f0_1001",
   "namaster-0.9-py36h94a39f0_1002",
   "namaster-0.9-py36hf3f1cc3_1000",
   "namaster-0.9-py36hf3f1cc3_1001",
   "namaster-0.9-py36hf3f1cc3_1002",
   "namaster-0.9-py37h80e476a_0",
   "namaster-0.9-py37h80e476a_1",
   "namaster-0.9-py37h94a39f0_1000",
   "namaster-0.9-py37h94a39f0_1001",
   "namaster-0.9-py37h94a39f0_1002",
   "namaster-0.9-py37hf3f1cc3_1000",
   "namaster-0.9-py37hf3f1cc3_1001",
   "namaster-0.9-py37hf3f1cc3_1002",
   "namaster-1.0-py36h1c7146f_1",
   "namaster-1.0-py36h1f597ea_0",
   "namaster-1.0-py36h68ff454_4",
   "namaster-1.0-py36ha52e2a5_2",
   "namaster-1.0-py36ha52e2a5_3",
   "namaster-1.0-py36ha6ad5ee_4",
   "namaster-1.0-py36hcac20d5_2",
   "namaster-1.0-py36hcac20d5_3",
   "namaster-1.0-py36hcac20d5_4",
   "namaster-1.0-py36hd5a618d_4",
   "namaster-1.0-py36he2b8767_0",
   "namaster-1.0-py36heade8f8_1",
   "namaster-1.0-py37h1c7146f_1",
   "namaster-1.0-py37h1f597ea_0",
   "namaster-1.0-py37h68ff454_4",
   "namaster-1.0-py37ha52e2a5_2",
   "namaster-1.0-py37ha52e2a5_3",
   "namaster-1.0-py37ha6ad5ee_4",
   "namaster-1.0-py37hcac20d5_3",
   "namaster-1.0-py37hcac20d5_4",
   "namaster-1.0-py37hd5a618d_4",
   "namaster-1.0-py37he2b8767_0",
   "namaster-1.0-py37heade8f8_1",
   "namaster-1.0-py38h68ff454_4",
   "namaster-1.0-py38hd5a618d_4",
   "namaster-1.0.1-py36h2231e5d_1",
   "namaster-1.0.1-py36h29f0320_1",
   "namaster-1.0.1-py36h68ff454_0",
   "namaster-1.0.1-py36hd5a618d_0",
   "namaster-1.0.1-py37h2231e5d_1",
   "namaster-1.0.1-py37h29f0320_1",
   "namaster-1.0.1-py37h68ff454_0",
   "namaster-1.0.1-py37hd5a618d_0",
   "namaster-1.0.1-py38h2231e5d_1",
   "namaster-1.0.1-py38h29f0320_1",
   "namaster-1.0.1-py38h68ff454_0",
   "namaster-1.0.1-py38hd5a618d_0",
   "namaster-1.0.2-py36h7a5739d_0",
   "namaster-1.0.2-py36h7a5739d_1",
   "namaster-1.0.2-py36h901bbe3_0",
   "namaster-1.0.2-py36h901bbe3_1",
   "namaster-1.0.2-py37h59fce41_0",
   "namaster-1.0.2-py37h59fce41_1",
   "namaster-1.0.2-py37h7e6a3ff_0",
   "namaster-1.0.2-py37h7e6a3ff_1",
   "namaster-1.0.2-py38hd03a703_0",
   "namaster-1.0.2-py38hd03a703_1",
   "namaster-1.0.2-py38hd979682_0",
   "namaster-1.0.2-py38hd979682_1",
   "namaster-1.1-py36h524736b_1",
   "namaster-1.1-py36h9cd7356_1",
   "namaster-1.1-py36hc23624d_0",
   "namaster-1.1-py36hd80d3ad_0",
   "namaster-1.1-py37h535f4d9_0",
   "namaster-1.1-py37h6399f61_0",
   "namaster-1.1-py37h8779778_1",
   "namaster-1.1-py37h9df0149_1",
   "namaster-1.1-py38h1e5085f_0",
   "namaster-1.1-py38h21af0b8_1",
   "namaster-1.1-py38h7f616b5_1",
   "namaster-1.1-py38hebd3e1f_0",
   "namaster-1.1-py39h0623892_1",
   "namaster-1.1-py39h7a3d968_1",
   "namaster-1.2-py36hc189036_0",
   "namaster-1.2-py36hffe08b1_0",
   "namaster-1.2-py37h9fdd626_0",
   "namaster-1.2-py37hed5e69e_0",
   "namaster-1.2-py38h0b658a1_0",
   "namaster-1.2-py38h503a07d_0",
   "namaster-1.2-py39h5261cd8_0",
   "namaster-1.2-py39h825e959_0"
  ]
 }
}