{
 "funcparserlib":{
  "__set__":true,
  "elements":[
   "funcparserlib-0.3.6-py27_0",
   "funcparserlib-0.3.6-py36h9f0ad1d_1",
   "funcparserlib-0.3.6-py36h9f0ad1d_2",
   "funcparserlib-0.3.6-py37_0",
   "funcparserlib-0.3.6-py37hc8dfbb8_1",
   "funcparserlib-0.3.6-py37hf985489_3"
  ]
 },
 "funcparserlib.lexer":{
  "__set__":true,
  "elements":[
   "funcparserlib-0.3.6-py27_0",
   "funcparserlib-0.3.6-py36h9f0ad1d_1",
   "funcparserlib-0.3.6-py36h9f0ad1d_2",
   "funcparserlib-0.3.6-py37_0",
   "funcparserlib-0.3.6-py37hc8dfbb8_1",
   "funcparserlib-0.3.6-py37hf985489_3"
  ]
 },
 "funcparserlib.parser":{
  "__set__":true,
  "elements":[
   "funcparserlib-0.3.6-py27_0",
   "funcparserlib-0.3.6-py36h9f0ad1d_1",
   "funcparserlib-0.3.6-py36h9f0ad1d_2",
   "funcparserlib-0.3.6-py37_0",
   "funcparserlib-0.3.6-py37hc8dfbb8_1",
   "funcparserlib-0.3.6-py37hf985489_3"
  ]
 },
 "funcparserlib.tests":{
  "__set__":true,
  "elements":[
   "funcparserlib-0.3.6-py27_0",
   "funcparserlib-0.3.6-py36h9f0ad1d_1",
   "funcparserlib-0.3.6-py36h9f0ad1d_2",
   "funcparserlib-0.3.6-py37_0",
   "funcparserlib-0.3.6-py37hc8dfbb8_1",
   "funcparserlib-0.3.6-py37hf985489_3"
  ]
 },
 "funcparserlib.tests.dot":{
  "__set__":true,
  "elements":[
   "funcparserlib-0.3.6-py27_0",
   "funcparserlib-0.3.6-py36h9f0ad1d_1",
   "funcparserlib-0.3.6-py36h9f0ad1d_2",
   "funcparserlib-0.3.6-py37_0",
   "funcparserlib-0.3.6-py37hc8dfbb8_1",
   "funcparserlib-0.3.6-py37hf985489_3"
  ]
 },
 "funcparserlib.tests.json":{
  "__set__":true,
  "elements":[
   "funcparserlib-0.3.6-py27_0",
   "funcparserlib-0.3.6-py36h9f0ad1d_1",
   "funcparserlib-0.3.6-py36h9f0ad1d_2",
   "funcparserlib-0.3.6-py37_0",
   "funcparserlib-0.3.6-py37hc8dfbb8_1",
   "funcparserlib-0.3.6-py37hf985489_3"
  ]
 },
 "funcparserlib.tests.test_dot":{
  "__set__":true,
  "elements":[
   "funcparserlib-0.3.6-py27_0",
   "funcparserlib-0.3.6-py36h9f0ad1d_1",
   "funcparserlib-0.3.6-py36h9f0ad1d_2",
   "funcparserlib-0.3.6-py37_0",
   "funcparserlib-0.3.6-py37hc8dfbb8_1",
   "funcparserlib-0.3.6-py37hf985489_3"
  ]
 },
 "funcparserlib.tests.test_json":{
  "__set__":true,
  "elements":[
   "funcparserlib-0.3.6-py27_0",
   "funcparserlib-0.3.6-py36h9f0ad1d_1",
   "funcparserlib-0.3.6-py36h9f0ad1d_2",
   "funcparserlib-0.3.6-py37_0",
   "funcparserlib-0.3.6-py37hc8dfbb8_1",
   "funcparserlib-0.3.6-py37hf985489_3"
  ]
 },
 "funcparserlib.tests.test_parsing":{
  "__set__":true,
  "elements":[
   "funcparserlib-0.3.6-py27_0",
   "funcparserlib-0.3.6-py36h9f0ad1d_1",
   "funcparserlib-0.3.6-py36h9f0ad1d_2",
   "funcparserlib-0.3.6-py37_0",
   "funcparserlib-0.3.6-py37hc8dfbb8_1",
   "funcparserlib-0.3.6-py37hf985489_3"
  ]
 },
 "funcparserlib.util":{
  "__set__":true,
  "elements":[
   "funcparserlib-0.3.6-py27_0",
   "funcparserlib-0.3.6-py36h9f0ad1d_1",
   "funcparserlib-0.3.6-py36h9f0ad1d_2",
   "funcparserlib-0.3.6-py37_0",
   "funcparserlib-0.3.6-py37hc8dfbb8_1",
   "funcparserlib-0.3.6-py37hf985489_3"
  ]
 }
}