{
 "_pytest":{
  "__set__":true,
  "elements":[
   "pyamg",
   "pytest",
   "pytest-jupyter"
  ]
 },
 "_pytest._argcomplete":{
  "__set__":true,
  "elements":[
   "pyamg",
   "pytest",
   "pytest-jupyter"
  ]
 },
 "_pytest._code":{
  "__set__":true,
  "elements":[
   "pyamg",
   "pytest",
   "pytest-jupyter"
  ]
 },
 "_pytest._code._py2traceback":{
  "__set__":true,
  "elements":[
   "pyamg",
   "pytest"
  ]
 },
 "_pytest._code.code":{
  "__set__":true,
  "elements":[
   "pyamg",
   "pytest",
   "pytest-jupyter"
  ]
 },
 "_pytest._code.source":{
  "__set__":true,
  "elements":[
   "pyamg",
   "pytest",
   "pytest-jupyter"
  ]
 },
 "_pytest._io":{
  "__set__":true,
  "elements":[
   "pytest",
   "pytest-jupyter"
  ]
 },
 "_pytest._io.saferepr":{
  "__set__":true,
  "elements":[
   "pytest",
   "pytest-jupyter"
  ]
 },
 "_pytest._io.terminalwriter":{
  "__set__":true,
  "elements":[
   "pytest",
   "pytest-jupyter"
  ]
 },
 "_pytest._io.wcwidth":{
  "__set__":true,
  "elements":[
   "pytest",
   "pytest-jupyter"
  ]
 },
 "_pytest._pluggy":{
  "__set__":true,
  "elements":[
   "pytest"
  ]
 },
 "_pytest._py":{
  "__set__":true,
  "elements":[
   "pytest",
   "pytest-jupyter"
  ]
 },
 "_pytest._py.error":{
  "__set__":true,
  "elements":[
   "pytest",
   "pytest-jupyter"
  ]
 },
 "_pytest._py.path":{
  "__set__":true,
  "elements":[
   "pytest",
   "pytest-jupyter"
  ]
 },
 "_pytest._version":{
  "__set__":true,
  "elements":[
   "pyamg",
   "pytest",
   "pytest-jupyter"
  ]
 },
 "_pytest.assertion":{
  "__set__":true,
  "elements":[
   "pyamg",
   "pytest",
   "pytest-jupyter"
  ]
 },
 "_pytest.assertion.reinterpret":{
  "__set__":true,
  "elements":[
   "pytest"
  ]
 },
 "_pytest.assertion.rewrite":{
  "__set__":true,
  "elements":[
   "pyamg",
   "pytest",
   "pytest-jupyter"
  ]
 },
 "_pytest.assertion.truncate":{
  "__set__":true,
  "elements":[
   "pyamg",
   "pytest",
   "pytest-jupyter"
  ]
 },
 "_pytest.assertion.util":{
  "__set__":true,
  "elements":[
   "pyamg",
   "pytest",
   "pytest-jupyter"
  ]
 },
 "_pytest.cacheprovider":{
  "__set__":true,
  "elements":[
   "pyamg",
   "pytest",
   "pytest-jupyter"
  ]
 },
 "_pytest.capture":{
  "__set__":true,
  "elements":[
   "pyamg",
   "pytest",
   "pytest-jupyter"
  ]
 },
 "_pytest.compat":{
  "__set__":true,
  "elements":[
   "pyamg",
   "pytest",
   "pytest-jupyter"
  ]
 },
 "_pytest.config":{
  "__set__":true,
  "elements":[
   "pyamg",
   "pytest",
   "pytest-jupyter"
  ]
 },
 "_pytest.config.argparsing":{
  "__set__":true,
  "elements":[
   "pyamg",
   "pytest",
   "pytest-jupyter"
  ]
 },
 "_pytest.config.compat":{
  "__set__":true,
  "elements":[
   "pytest",
   "pytest-jupyter"
  ]
 },
 "_pytest.config.exceptions":{
  "__set__":true,
  "elements":[
   "pyamg",
   "pytest",
   "pytest-jupyter"
  ]
 },
 "_pytest.config.findpaths":{
  "__set__":true,
  "elements":[
   "pyamg",
   "pytest",
   "pytest-jupyter"
  ]
 },
 "_pytest.debugging":{
  "__set__":true,
  "elements":[
   "pyamg",
   "pytest",
   "pytest-jupyter"
  ]
 },
 "_pytest.deprecated":{
  "__set__":true,
  "elements":[
   "pyamg",
   "pytest",
   "pytest-jupyter"
  ]
 },
 "_pytest.doctest":{
  "__set__":true,
  "elements":[
   "pyamg",
   "pytest",
   "pytest-jupyter"
  ]
 },
 "_pytest.experiments":{
  "__set__":true,
  "elements":[
   "pytest"
  ]
 },
 "_pytest.faulthandler":{
  "__set__":true,
  "elements":[
   "pytest",
   "pytest-jupyter"
  ]
 },
 "_pytest.fixtures":{
  "__set__":true,
  "elements":[
   "pyamg",
   "pytest",
   "pytest-jupyter"
  ]
 },
 "_pytest.freeze_support":{
  "__set__":true,
  "elements":[
   "pyamg",
   "pytest",
   "pytest-jupyter"
  ]
 },
 "_pytest.genscript":{
  "__set__":true,
  "elements":[
   "pytest"
  ]
 },
 "_pytest.helpconfig":{
  "__set__":true,
  "elements":[
   "pyamg",
   "pytest",
   "pytest-jupyter"
  ]
 },
 "_pytest.hookspec":{
  "__set__":true,
  "elements":[
   "pyamg",
   "pytest",
   "pytest-jupyter"
  ]
 },
 "_pytest.junitxml":{
  "__set__":true,
  "elements":[
   "pyamg",
   "pytest",
   "pytest-jupyter"
  ]
 },
 "_pytest.legacypath":{
  "__set__":true,
  "elements":[
   "pytest",
   "pytest-jupyter"
  ]
 },
 "_pytest.logging":{
  "__set__":true,
  "elements":[
   "pyamg",
   "pytest",
   "pytest-jupyter"
  ]
 },
 "_pytest.main":{
  "__set__":true,
  "elements":[
   "pyamg",
   "pytest",
   "pytest-jupyter"
  ]
 },
 "_pytest.mark":{
  "__set__":true,
  "elements":[
   "pyamg",
   "pytest",
   "pytest-jupyter"
  ]
 },
 "_pytest.mark.evaluate":{
  "__set__":true,
  "elements":[
   "pyamg",
   "pytest"
  ]
 },
 "_pytest.mark.expression":{
  "__set__":true,
  "elements":[
   "pytest",
   "pytest-jupyter"
  ]
 },
 "_pytest.mark.legacy":{
  "__set__":true,
  "elements":[
   "pyamg",
   "pytest"
  ]
 },
 "_pytest.mark.structures":{
  "__set__":true,
  "elements":[
   "pyamg",
   "pytest",
   "pytest-jupyter"
  ]
 },
 "_pytest.monkeypatch":{
  "__set__":true,
  "elements":[
   "pyamg",
   "pytest",
   "pytest-jupyter"
  ]
 },
 "_pytest.nodes":{
  "__set__":true,
  "elements":[
   "pyamg",
   "pytest",
   "pytest-jupyter"
  ]
 },
 "_pytest.nose":{
  "__set__":true,
  "elements":[
   "pyamg",
   "pytest",
   "pytest-jupyter"
  ]
 },
 "_pytest.outcomes":{
  "__set__":true,
  "elements":[
   "pyamg",
   "pytest",
   "pytest-jupyter"
  ]
 },
 "_pytest.pastebin":{
  "__set__":true,
  "elements":[
   "pyamg",
   "pytest",
   "pytest-jupyter"
  ]
 },
 "_pytest.pathlib":{
  "__set__":true,
  "elements":[
   "pyamg",
   "pytest",
   "pytest-jupyter"
  ]
 },
 "_pytest.paths":{
  "__set__":true,
  "elements":[
   "pytest"
  ]
 },
 "_pytest.pdb":{
  "__set__":true,
  "elements":[
   "pytest"
  ]
 },
 "_pytest.pytester":{
  "__set__":true,
  "elements":[
   "pyamg",
   "pytest",
   "pytest-jupyter"
  ]
 },
 "_pytest.pytester_assertions":{
  "__set__":true,
  "elements":[
   "pytest",
   "pytest-jupyter"
  ]
 },
 "_pytest.python":{
  "__set__":true,
  "elements":[
   "pyamg",
   "pytest",
   "pytest-jupyter"
  ]
 },
 "_pytest.python_api":{
  "__set__":true,
  "elements":[
   "pyamg",
   "pytest",
   "pytest-jupyter"
  ]
 },
 "_pytest.python_path":{
  "__set__":true,
  "elements":[
   "pytest",
   "pytest-jupyter"
  ]
 },
 "_pytest.pythonpath":{
  "__set__":true,
  "elements":[
   "pytest"
  ]
 },
 "_pytest.recwarn":{
  "__set__":true,
  "elements":[
   "pyamg",
   "pytest",
   "pytest-jupyter"
  ]
 },
 "_pytest.reports":{
  "__set__":true,
  "elements":[
   "pyamg",
   "pytest",
   "pytest-jupyter"
  ]
 },
 "_pytest.resultlog":{
  "__set__":true,
  "elements":[
   "pyamg",
   "pytest"
  ]
 },
 "_pytest.runner":{
  "__set__":true,
  "elements":[
   "pyamg",
   "pytest",
   "pytest-jupyter"
  ]
 },
 "_pytest.scope":{
  "__set__":true,
  "elements":[
   "pytest",
   "pytest-jupyter"
  ]
 },
 "_pytest.setuponly":{
  "__set__":true,
  "elements":[
   "pyamg",
   "pytest",
   "pytest-jupyter"
  ]
 },
 "_pytest.setupplan":{
  "__set__":true,
  "elements":[
   "pyamg",
   "pytest",
   "pytest-jupyter"
  ]
 },
 "_pytest.skipping":{
  "__set__":true,
  "elements":[
   "pyamg",
   "pytest",
   "pytest-jupyter"
  ]
 },
 "_pytest.standalonetemplate":{
  "__set__":true,
  "elements":[
   "pytest"
  ]
 },
 "_pytest.stash":{
  "__set__":true,
  "elements":[
   "pytest",
   "pytest-jupyter"
  ]
 },
 "_pytest.stepwise":{
  "__set__":true,
  "elements":[
   "pyamg",
   "pytest",
   "pytest-jupyter"
  ]
 },
 "_pytest.store":{
  "__set__":true,
  "elements":[
   "pytest"
  ]
 },
 "_pytest.terminal":{
  "__set__":true,
  "elements":[
   "pyamg",
   "pytest",
   "pytest-jupyter"
  ]
 },
 "_pytest.threadexception":{
  "__set__":true,
  "elements":[
   "pytest",
   "pytest-jupyter"
  ]
 },
 "_pytest.timing":{
  "__set__":true,
  "elements":[
   "pytest",
   "pytest-jupyter"
  ]
 },
 "_pytest.tmpdir":{
  "__set__":true,
  "elements":[
   "pyamg",
   "pytest",
   "pytest-jupyter"
  ]
 },
 "_pytest.unittest":{
  "__set__":true,
  "elements":[
   "pyamg",
   "pytest",
   "pytest-jupyter"
  ]
 },
 "_pytest.unraisableexception":{
  "__set__":true,
  "elements":[
   "pytest",
   "pytest-jupyter"
  ]
 },
 "_pytest.vendored_packages":{
  "__set__":true,
  "elements":[
   "pytest"
  ]
 },
 "_pytest.vendored_packages.pluggy":{
  "__set__":true,
  "elements":[
   "pytest"
  ]
 },
 "_pytest.warning_types":{
  "__set__":true,
  "elements":[
   "pyamg",
   "pytest",
   "pytest-jupyter"
  ]
 },
 "_pytest.warnings":{
  "__set__":true,
  "elements":[
   "pyamg",
   "pytest",
   "pytest-jupyter"
  ]
 },
 "_pytest_mock_version":{
  "__set__":true,
  "elements":[
   "pytest-mock"
  ]
 }
}