{
 "avalanche":{
  "__set__":true,
  "elements":[
   "avalanche-lib"
  ]
 },
 "avalanche.benchmarks":{
  "__set__":true,
  "elements":[
   "avalanche-lib"
  ]
 },
 "avalanche.benchmarks.classic":{
  "__set__":true,
  "elements":[
   "avalanche-lib"
  ]
 },
 "avalanche.benchmarks.classic.ccifar10":{
  "__set__":true,
  "elements":[
   "avalanche-lib"
  ]
 },
 "avalanche.benchmarks.classic.ccifar100":{
  "__set__":true,
  "elements":[
   "avalanche-lib"
  ]
 },
 "avalanche.benchmarks.classic.ccub200":{
  "__set__":true,
  "elements":[
   "avalanche-lib"
  ]
 },
 "avalanche.benchmarks.classic.cfashion_mnist":{
  "__set__":true,
  "elements":[
   "avalanche-lib"
  ]
 },
 "avalanche.benchmarks.classic.cimagenet":{
  "__set__":true,
  "elements":[
   "avalanche-lib"
  ]
 },
 "avalanche.benchmarks.classic.cinaturalist":{
  "__set__":true,
  "elements":[
   "avalanche-lib"
  ]
 },
 "avalanche.benchmarks.classic.classic_benchmarks_utils":{
  "__set__":true,
  "elements":[
   "avalanche-lib"
  ]
 },
 "avalanche.benchmarks.classic.clear":{
  "__set__":true,
  "elements":[
   "avalanche-lib"
  ]
 },
 "avalanche.benchmarks.classic.cmnist":{
  "__set__":true,
  "elements":[
   "avalanche-lib"
  ]
 },
 "avalanche.benchmarks.classic.comniglot":{
  "__set__":true,
  "elements":[
   "avalanche-lib"
  ]
 },
 "avalanche.benchmarks.classic.core50":{
  "__set__":true,
  "elements":[
   "avalanche-lib"
  ]
 },
 "avalanche.benchmarks.classic.ctiny_imagenet":{
  "__set__":true,
  "elements":[
   "avalanche-lib"
  ]
 },
 "avalanche.benchmarks.classic.ctrl":{
  "__set__":true,
  "elements":[
   "avalanche-lib"
  ]
 },
 "avalanche.benchmarks.classic.endless_cl_sim":{
  "__set__":true,
  "elements":[
   "avalanche-lib"
  ]
 },
 "avalanche.benchmarks.classic.ex_model":{
  "__set__":true,
  "elements":[
   "avalanche-lib"
  ]
 },
 "avalanche.benchmarks.classic.openloris":{
  "__set__":true,
  "elements":[
   "avalanche-lib"
  ]
 },
 "avalanche.benchmarks.classic.stream51":{
  "__set__":true,
  "elements":[
   "avalanche-lib"
  ]
 },
 "avalanche.benchmarks.datasets":{
  "__set__":true,
  "elements":[
   "avalanche-lib"
  ]
 },
 "avalanche.benchmarks.datasets.clear":{
  "__set__":true,
  "elements":[
   "avalanche-lib"
  ]
 },
 "avalanche.benchmarks.datasets.clear.clear":{
  "__set__":true,
  "elements":[
   "avalanche-lib"
  ]
 },
 "avalanche.benchmarks.datasets.clear.clear_data":{
  "__set__":true,
  "elements":[
   "avalanche-lib"
  ]
 },
 "avalanche.benchmarks.datasets.core50":{
  "__set__":true,
  "elements":[
   "avalanche-lib"
  ]
 },
 "avalanche.benchmarks.datasets.core50.core50":{
  "__set__":true,
  "elements":[
   "avalanche-lib"
  ]
 },
 "avalanche.benchmarks.datasets.core50.core50_data":{
  "__set__":true,
  "elements":[
   "avalanche-lib"
  ]
 },
 "avalanche.benchmarks.datasets.cub200":{
  "__set__":true,
  "elements":[
   "avalanche-lib"
  ]
 },
 "avalanche.benchmarks.datasets.cub200.cub200":{
  "__set__":true,
  "elements":[
   "avalanche-lib"
  ]
 },
 "avalanche.benchmarks.datasets.dataset_utils":{
  "__set__":true,
  "elements":[
   "avalanche-lib"
  ]
 },
 "avalanche.benchmarks.datasets.downloadable_dataset":{
  "__set__":true,
  "elements":[
   "avalanche-lib"
  ]
 },
 "avalanche.benchmarks.datasets.endless_cl_sim":{
  "__set__":true,
  "elements":[
   "avalanche-lib"
  ]
 },
 "avalanche.benchmarks.datasets.endless_cl_sim.endless_cl_sim":{
  "__set__":true,
  "elements":[
   "avalanche-lib"
  ]
 },
 "avalanche.benchmarks.datasets.endless_cl_sim.endless_cl_sim_data":{
  "__set__":true,
  "elements":[
   "avalanche-lib"
  ]
 },
 "avalanche.benchmarks.datasets.imagenet_data":{
  "__set__":true,
  "elements":[
   "avalanche-lib"
  ]
 },
 "avalanche.benchmarks.datasets.inaturalist":{
  "__set__":true,
  "elements":[
   "avalanche-lib"
  ]
 },
 "avalanche.benchmarks.datasets.inaturalist.inaturalist":{
  "__set__":true,
  "elements":[
   "avalanche-lib"
  ]
 },
 "avalanche.benchmarks.datasets.inaturalist.inaturalist_data":{
  "__set__":true,
  "elements":[
   "avalanche-lib"
  ]
 },
 "avalanche.benchmarks.datasets.lvis_dataset":{
  "__set__":true,
  "elements":[
   "avalanche-lib"
  ]
 },
 "avalanche.benchmarks.datasets.lvis_dataset.lvis_data":{
  "__set__":true,
  "elements":[
   "avalanche-lib"
  ]
 },
 "avalanche.benchmarks.datasets.lvis_dataset.lvis_dataset":{
  "__set__":true,
  "elements":[
   "avalanche-lib"
  ]
 },
 "avalanche.benchmarks.datasets.mini_imagenet":{
  "__set__":true,
  "elements":[
   "avalanche-lib"
  ]
 },
 "avalanche.benchmarks.datasets.mini_imagenet.mini_imagenet":{
  "__set__":true,
  "elements":[
   "avalanche-lib"
  ]
 },
 "avalanche.benchmarks.datasets.mini_imagenet.mini_imagenet_data":{
  "__set__":true,
  "elements":[
   "avalanche-lib"
  ]
 },
 "avalanche.benchmarks.datasets.omniglot":{
  "__set__":true,
  "elements":[
   "avalanche-lib"
  ]
 },
 "avalanche.benchmarks.datasets.openloris":{
  "__set__":true,
  "elements":[
   "avalanche-lib"
  ]
 },
 "avalanche.benchmarks.datasets.openloris.openloris":{
  "__set__":true,
  "elements":[
   "avalanche-lib"
  ]
 },
 "avalanche.benchmarks.datasets.openloris.openloris_data":{
  "__set__":true,
  "elements":[
   "avalanche-lib"
  ]
 },
 "avalanche.benchmarks.datasets.penn_fudan":{
  "__set__":true,
  "elements":[
   "avalanche-lib"
  ]
 },
 "avalanche.benchmarks.datasets.penn_fudan.penn_fudan_data":{
  "__set__":true,
  "elements":[
   "avalanche-lib"
  ]
 },
 "avalanche.benchmarks.datasets.penn_fudan.penn_fudan_dataset":{
  "__set__":true,
  "elements":[
   "avalanche-lib"
  ]
 },
 "avalanche.benchmarks.datasets.stream51":{
  "__set__":true,
  "elements":[
   "avalanche-lib"
  ]
 },
 "avalanche.benchmarks.datasets.stream51.stream51":{
  "__set__":true,
  "elements":[
   "avalanche-lib"
  ]
 },
 "avalanche.benchmarks.datasets.stream51.stream51_data":{
  "__set__":true,
  "elements":[
   "avalanche-lib"
  ]
 },
 "avalanche.benchmarks.datasets.tiny_imagenet":{
  "__set__":true,
  "elements":[
   "avalanche-lib"
  ]
 },
 "avalanche.benchmarks.datasets.tiny_imagenet.tiny_imagenet":{
  "__set__":true,
  "elements":[
   "avalanche-lib"
  ]
 },
 "avalanche.benchmarks.datasets.torchvision_wrapper":{
  "__set__":true,
  "elements":[
   "avalanche-lib"
  ]
 },
 "avalanche.benchmarks.generators":{
  "__set__":true,
  "elements":[
   "avalanche-lib"
  ]
 },
 "avalanche.benchmarks.generators.benchmark_generators":{
  "__set__":true,
  "elements":[
   "avalanche-lib"
  ]
 },
 "avalanche.benchmarks.generators.scenario_generators":{
  "__set__":true,
  "elements":[
   "avalanche-lib"
  ]
 },
 "avalanche.benchmarks.scenarios":{
  "__set__":true,
  "elements":[
   "avalanche-lib"
  ]
 },
 "avalanche.benchmarks.scenarios.classification_scenario":{
  "__set__":true,
  "elements":[
   "avalanche-lib"
  ]
 },
 "avalanche.benchmarks.scenarios.detection_scenario":{
  "__set__":true,
  "elements":[
   "avalanche-lib"
  ]
 },
 "avalanche.benchmarks.scenarios.exmodel_scenario":{
  "__set__":true,
  "elements":[
   "avalanche-lib"
  ]
 },
 "avalanche.benchmarks.scenarios.generic_benchmark_creation":{
  "__set__":true,
  "elements":[
   "avalanche-lib"
  ]
 },
 "avalanche.benchmarks.scenarios.generic_definitions":{
  "__set__":true,
  "elements":[
   "avalanche-lib"
  ]
 },
 "avalanche.benchmarks.scenarios.generic_scenario":{
  "__set__":true,
  "elements":[
   "avalanche-lib"
  ]
 },
 "avalanche.benchmarks.scenarios.generic_scenario_creation":{
  "__set__":true,
  "elements":[
   "avalanche-lib"
  ]
 },
 "avalanche.benchmarks.scenarios.lazy_dataset_sequence":{
  "__set__":true,
  "elements":[
   "avalanche-lib"
  ]
 },
 "avalanche.benchmarks.scenarios.new_classes":{
  "__set__":true,
  "elements":[
   "avalanche-lib"
  ]
 },
 "avalanche.benchmarks.scenarios.new_classes.nc_scenario":{
  "__set__":true,
  "elements":[
   "avalanche-lib"
  ]
 },
 "avalanche.benchmarks.scenarios.new_classes.nc_utils":{
  "__set__":true,
  "elements":[
   "avalanche-lib"
  ]
 },
 "avalanche.benchmarks.scenarios.new_instances":{
  "__set__":true,
  "elements":[
   "avalanche-lib"
  ]
 },
 "avalanche.benchmarks.scenarios.new_instances.ni_scenario":{
  "__set__":true,
  "elements":[
   "avalanche-lib"
  ]
 },
 "avalanche.benchmarks.scenarios.new_instances.ni_utils":{
  "__set__":true,
  "elements":[
   "avalanche-lib"
  ]
 },
 "avalanche.benchmarks.scenarios.online_scenario":{
  "__set__":true,
  "elements":[
   "avalanche-lib"
  ]
 },
 "avalanche.benchmarks.scenarios.rl_scenario":{
  "__set__":true,
  "elements":[
   "avalanche-lib"
  ]
 },
 "avalanche.benchmarks.scenarios.scenario_utils":{
  "__set__":true,
  "elements":[
   "avalanche-lib"
  ]
 },
 "avalanche.benchmarks.utils":{
  "__set__":true,
  "elements":[
   "avalanche-lib"
  ]
 },
 "avalanche.benchmarks.utils.adaptive_transform":{
  "__set__":true,
  "elements":[
   "avalanche-lib"
  ]
 },
 "avalanche.benchmarks.utils.avalanche_dataset":{
  "__set__":true,
  "elements":[
   "avalanche-lib"
  ]
 },
 "avalanche.benchmarks.utils.data_loader":{
  "__set__":true,
  "elements":[
   "avalanche-lib"
  ]
 },
 "avalanche.benchmarks.utils.dataset_definitions":{
  "__set__":true,
  "elements":[
   "avalanche-lib"
  ]
 },
 "avalanche.benchmarks.utils.dataset_utils":{
  "__set__":true,
  "elements":[
   "avalanche-lib"
  ]
 },
 "avalanche.benchmarks.utils.datasets_from_filelists":{
  "__set__":true,
  "elements":[
   "avalanche-lib"
  ]
 },
 "avalanche.benchmarks.utils.torchvision_wrapper":{
  "__set__":true,
  "elements":[
   "avalanche-lib"
  ]
 },
 "avalanche.benchmarks.utils.utils":{
  "__set__":true,
  "elements":[
   "avalanche-lib"
  ]
 },
 "avalanche.core":{
  "__set__":true,
  "elements":[
   "avalanche-lib"
  ]
 },
 "avalanche.evaluation":{
  "__set__":true,
  "elements":[
   "avalanche-lib"
  ]
 },
 "avalanche.evaluation.metric_definitions":{
  "__set__":true,
  "elements":[
   "avalanche-lib"
  ]
 },
 "avalanche.evaluation.metric_results":{
  "__set__":true,
  "elements":[
   "avalanche-lib"
  ]
 },
 "avalanche.evaluation.metric_utils":{
  "__set__":true,
  "elements":[
   "avalanche-lib"
  ]
 },
 "avalanche.evaluation.metrics":{
  "__set__":true,
  "elements":[
   "avalanche-lib"
  ]
 },
 "avalanche.evaluation.metrics.accuracy":{
  "__set__":true,
  "elements":[
   "avalanche-lib"
  ]
 },
 "avalanche.evaluation.metrics.amca":{
  "__set__":true,
  "elements":[
   "avalanche-lib"
  ]
 },
 "avalanche.evaluation.metrics.checkpoint":{
  "__set__":true,
  "elements":[
   "avalanche-lib"
  ]
 },
 "avalanche.evaluation.metrics.class_accuracy":{
  "__set__":true,
  "elements":[
   "avalanche-lib"
  ]
 },
 "avalanche.evaluation.metrics.confusion_matrix":{
  "__set__":true,
  "elements":[
   "avalanche-lib"
  ]
 },
 "avalanche.evaluation.metrics.cpu_usage":{
  "__set__":true,
  "elements":[
   "avalanche-lib"
  ]
 },
 "avalanche.evaluation.metrics.detection":{
  "__set__":true,
  "elements":[
   "avalanche-lib"
  ]
 },
 "avalanche.evaluation.metrics.detection_evaluators":{
  "__set__":true,
  "elements":[
   "avalanche-lib"
  ]
 },
 "avalanche.evaluation.metrics.detection_evaluators.coco_evaluator":{
  "__set__":true,
  "elements":[
   "avalanche-lib"
  ]
 },
 "avalanche.evaluation.metrics.detection_evaluators.lvis_evaluator":{
  "__set__":true,
  "elements":[
   "avalanche-lib"
  ]
 },
 "avalanche.evaluation.metrics.disk_usage":{
  "__set__":true,
  "elements":[
   "avalanche-lib"
  ]
 },
 "avalanche.evaluation.metrics.forgetting_bwt":{
  "__set__":true,
  "elements":[
   "avalanche-lib"
  ]
 },
 "avalanche.evaluation.metrics.forward_transfer":{
  "__set__":true,
  "elements":[
   "avalanche-lib"
  ]
 },
 "avalanche.evaluation.metrics.gpu_usage":{
  "__set__":true,
  "elements":[
   "avalanche-lib"
  ]
 },
 "avalanche.evaluation.metrics.images_samples":{
  "__set__":true,
  "elements":[
   "avalanche-lib"
  ]
 },
 "avalanche.evaluation.metrics.labels_repartition":{
  "__set__":true,
  "elements":[
   "avalanche-lib"
  ]
 },
 "avalanche.evaluation.metrics.loss":{
  "__set__":true,
  "elements":[
   "avalanche-lib"
  ]
 },
 "avalanche.evaluation.metrics.mac":{
  "__set__":true,
  "elements":[
   "avalanche-lib"
  ]
 },
 "avalanche.evaluation.metrics.mean":{
  "__set__":true,
  "elements":[
   "avalanche-lib"
  ]
 },
 "avalanche.evaluation.metrics.mean_scores":{
  "__set__":true,
  "elements":[
   "avalanche-lib"
  ]
 },
 "avalanche.evaluation.metrics.ram_usage":{
  "__set__":true,
  "elements":[
   "avalanche-lib"
  ]
 },
 "avalanche.evaluation.metrics.timing":{
  "__set__":true,
  "elements":[
   "avalanche-lib"
  ]
 },
 "avalanche.evaluation.metrics.topk_acc":{
  "__set__":true,
  "elements":[
   "avalanche-lib"
  ]
 },
 "avalanche.evaluation.plot_utils":{
  "__set__":true,
  "elements":[
   "avalanche-lib"
  ]
 },
 "avalanche.logging":{
  "__set__":true,
  "elements":[
   "avalanche-lib"
  ]
 },
 "avalanche.logging.base_logger":{
  "__set__":true,
  "elements":[
   "avalanche-lib"
  ]
 },
 "avalanche.logging.csv_logger":{
  "__set__":true,
  "elements":[
   "avalanche-lib"
  ]
 },
 "avalanche.logging.interactive_logging":{
  "__set__":true,
  "elements":[
   "avalanche-lib"
  ]
 },
 "avalanche.logging.tensorboard_logger":{
  "__set__":true,
  "elements":[
   "avalanche-lib"
  ]
 },
 "avalanche.logging.text_logging":{
  "__set__":true,
  "elements":[
   "avalanche-lib"
  ]
 },
 "avalanche.logging.wandb_logger":{
  "__set__":true,
  "elements":[
   "avalanche-lib"
  ]
 },
 "avalanche.models":{
  "__set__":true,
  "elements":[
   "avalanche-lib"
  ]
 },
 "avalanche.models.base_model":{
  "__set__":true,
  "elements":[
   "avalanche-lib"
  ]
 },
 "avalanche.models.batch_renorm":{
  "__set__":true,
  "elements":[
   "avalanche-lib"
  ]
 },
 "avalanche.models.dynamic_modules":{
  "__set__":true,
  "elements":[
   "avalanche-lib"
  ]
 },
 "avalanche.models.dynamic_optimizers":{
  "__set__":true,
  "elements":[
   "avalanche-lib"
  ]
 },
 "avalanche.models.generator":{
  "__set__":true,
  "elements":[
   "avalanche-lib"
  ]
 },
 "avalanche.models.helper_method":{
  "__set__":true,
  "elements":[
   "avalanche-lib"
  ]
 },
 "avalanche.models.icarl_resnet":{
  "__set__":true,
  "elements":[
   "avalanche-lib"
  ]
 },
 "avalanche.models.lenet5":{
  "__set__":true,
  "elements":[
   "avalanche-lib"
  ]
 },
 "avalanche.models.mlp_tiny_imagenet":{
  "__set__":true,
  "elements":[
   "avalanche-lib"
  ]
 },
 "avalanche.models.mobilenetv1":{
  "__set__":true,
  "elements":[
   "avalanche-lib"
  ]
 },
 "avalanche.models.ncm_classifier":{
  "__set__":true,
  "elements":[
   "avalanche-lib"
  ]
 },
 "avalanche.models.pnn":{
  "__set__":true,
  "elements":[
   "avalanche-lib"
  ]
 },
 "avalanche.models.pytorchcv_wrapper":{
  "__set__":true,
  "elements":[
   "avalanche-lib"
  ]
 },
 "avalanche.models.simple_cnn":{
  "__set__":true,
  "elements":[
   "avalanche-lib"
  ]
 },
 "avalanche.models.simple_mlp":{
  "__set__":true,
  "elements":[
   "avalanche-lib"
  ]
 },
 "avalanche.models.slda_resnet":{
  "__set__":true,
  "elements":[
   "avalanche-lib"
  ]
 },
 "avalanche.models.slim_resnet18":{
  "__set__":true,
  "elements":[
   "avalanche-lib"
  ]
 },
 "avalanche.models.utils":{
  "__set__":true,
  "elements":[
   "avalanche-lib"
  ]
 },
 "avalanche.training":{
  "__set__":true,
  "elements":[
   "avalanche-lib"
  ]
 },
 "avalanche.training.losses":{
  "__set__":true,
  "elements":[
   "avalanche-lib"
  ]
 },
 "avalanche.training.plugins":{
  "__set__":true,
  "elements":[
   "avalanche-lib"
  ]
 },
 "avalanche.training.plugins.agem":{
  "__set__":true,
  "elements":[
   "avalanche-lib"
  ]
 },
 "avalanche.training.plugins.clock":{
  "__set__":true,
  "elements":[
   "avalanche-lib"
  ]
 },
 "avalanche.training.plugins.cope":{
  "__set__":true,
  "elements":[
   "avalanche-lib"
  ]
 },
 "avalanche.training.plugins.cwr_star":{
  "__set__":true,
  "elements":[
   "avalanche-lib"
  ]
 },
 "avalanche.training.plugins.early_stopping":{
  "__set__":true,
  "elements":[
   "avalanche-lib"
  ]
 },
 "avalanche.training.plugins.evaluation":{
  "__set__":true,
  "elements":[
   "avalanche-lib"
  ]
 },
 "avalanche.training.plugins.ewc":{
  "__set__":true,
  "elements":[
   "avalanche-lib"
  ]
 },
 "avalanche.training.plugins.gdumb":{
  "__set__":true,
  "elements":[
   "avalanche-lib"
  ]
 },
 "avalanche.training.plugins.gem":{
  "__set__":true,
  "elements":[
   "avalanche-lib"
  ]
 },
 "avalanche.training.plugins.generative_replay":{
  "__set__":true,
  "elements":[
   "avalanche-lib"
  ]
 },
 "avalanche.training.plugins.gss_greedy":{
  "__set__":true,
  "elements":[
   "avalanche-lib"
  ]
 },
 "avalanche.training.plugins.lfl":{
  "__set__":true,
  "elements":[
   "avalanche-lib"
  ]
 },
 "avalanche.training.plugins.lr_scheduling":{
  "__set__":true,
  "elements":[
   "avalanche-lib"
  ]
 },
 "avalanche.training.plugins.lwf":{
  "__set__":true,
  "elements":[
   "avalanche-lib"
  ]
 },
 "avalanche.training.plugins.mas":{
  "__set__":true,
  "elements":[
   "avalanche-lib"
  ]
 },
 "avalanche.training.plugins.replay":{
  "__set__":true,
  "elements":[
   "avalanche-lib"
  ]
 },
 "avalanche.training.plugins.rwalk":{
  "__set__":true,
  "elements":[
   "avalanche-lib"
  ]
 },
 "avalanche.training.plugins.strategy_plugin":{
  "__set__":true,
  "elements":[
   "avalanche-lib"
  ]
 },
 "avalanche.training.plugins.synaptic_intelligence":{
  "__set__":true,
  "elements":[
   "avalanche-lib"
  ]
 },
 "avalanche.training.storage_policy":{
  "__set__":true,
  "elements":[
   "avalanche-lib"
  ]
 },
 "avalanche.training.supervised":{
  "__set__":true,
  "elements":[
   "avalanche-lib"
  ]
 },
 "avalanche.training.supervised.ar1":{
  "__set__":true,
  "elements":[
   "avalanche-lib"
  ]
 },
 "avalanche.training.supervised.cumulative":{
  "__set__":true,
  "elements":[
   "avalanche-lib"
  ]
 },
 "avalanche.training.supervised.deep_slda":{
  "__set__":true,
  "elements":[
   "avalanche-lib"
  ]
 },
 "avalanche.training.supervised.icarl":{
  "__set__":true,
  "elements":[
   "avalanche-lib"
  ]
 },
 "avalanche.training.supervised.joint_training":{
  "__set__":true,
  "elements":[
   "avalanche-lib"
  ]
 },
 "avalanche.training.supervised.lamaml":{
  "__set__":true,
  "elements":[
   "avalanche-lib"
  ]
 },
 "avalanche.training.supervised.naive_object_detection":{
  "__set__":true,
  "elements":[
   "avalanche-lib"
  ]
 },
 "avalanche.training.supervised.strategy_wrappers":{
  "__set__":true,
  "elements":[
   "avalanche-lib"
  ]
 },
 "avalanche.training.supervised.strategy_wrappers_online":{
  "__set__":true,
  "elements":[
   "avalanche-lib"
  ]
 },
 "avalanche.training.templates":{
  "__set__":true,
  "elements":[
   "avalanche-lib"
  ]
 },
 "avalanche.training.templates.base":{
  "__set__":true,
  "elements":[
   "avalanche-lib"
  ]
 },
 "avalanche.training.templates.base_online_sgd":{
  "__set__":true,
  "elements":[
   "avalanche-lib"
  ]
 },
 "avalanche.training.templates.base_sgd":{
  "__set__":true,
  "elements":[
   "avalanche-lib"
  ]
 },
 "avalanche.training.templates.online_supervised":{
  "__set__":true,
  "elements":[
   "avalanche-lib"
  ]
 },
 "avalanche.training.templates.supervised":{
  "__set__":true,
  "elements":[
   "avalanche-lib"
  ]
 },
 "avalanche.training.utils":{
  "__set__":true,
  "elements":[
   "avalanche-lib"
  ]
 }
}