{
 "bmi_wavewatch3":{
  "__set__":true,
  "elements":[
   "bmi-wavewatch3"
  ]
 },
 "bmi_wavewatch3._version":{
  "__set__":true,
  "elements":[
   "bmi-wavewatch3"
  ]
 },
 "bmi_wavewatch3.bmi":{
  "__set__":true,
  "elements":[
   "bmi-wavewatch3"
  ]
 },
 "bmi_wavewatch3.cli":{
  "__set__":true,
  "elements":[
   "bmi-wavewatch3"
  ]
 },
 "bmi_wavewatch3.downloader":{
  "__set__":true,
  "elements":[
   "bmi-wavewatch3"
  ]
 },
 "bmi_wavewatch3.errors":{
  "__set__":true,
  "elements":[
   "bmi-wavewatch3"
  ]
 },
 "bmi_wavewatch3.source":{
  "__set__":true,
  "elements":[
   "bmi-wavewatch3"
  ]
 },
 "bmi_wavewatch3.wavewatch3":{
  "__set__":true,
  "elements":[
   "bmi-wavewatch3"
  ]
 }
}