{
 "junifer":{
  "__set__":true,
  "elements":[
   "junifer"
  ]
 },
 "junifer._version":{
  "__set__":true,
  "elements":[
   "junifer"
  ]
 },
 "junifer.api":{
  "__set__":true,
  "elements":[
   "junifer"
  ]
 },
 "junifer.api.cli":{
  "__set__":true,
  "elements":[
   "junifer"
  ]
 },
 "junifer.api.decorators":{
  "__set__":true,
  "elements":[
   "junifer"
  ]
 },
 "junifer.api.functions":{
  "__set__":true,
  "elements":[
   "junifer"
  ]
 },
 "junifer.api.parser":{
  "__set__":true,
  "elements":[
   "junifer"
  ]
 },
 "junifer.api.utils":{
  "__set__":true,
  "elements":[
   "junifer"
  ]
 },
 "junifer.configs":{
  "__set__":true,
  "elements":[
   "junifer"
  ]
 },
 "junifer.configs.juseless":{
  "__set__":true,
  "elements":[
   "junifer"
  ]
 },
 "junifer.configs.juseless.datagrabbers":{
  "__set__":true,
  "elements":[
   "junifer"
  ]
 },
 "junifer.configs.juseless.datagrabbers.aomic_id1000_vbm":{
  "__set__":true,
  "elements":[
   "junifer"
  ]
 },
 "junifer.configs.juseless.datagrabbers.camcan_vbm":{
  "__set__":true,
  "elements":[
   "junifer"
  ]
 },
 "junifer.configs.juseless.datagrabbers.ixi_vbm":{
  "__set__":true,
  "elements":[
   "junifer"
  ]
 },
 "junifer.configs.juseless.datagrabbers.ucla":{
  "__set__":true,
  "elements":[
   "junifer"
  ]
 },
 "junifer.configs.juseless.datagrabbers.ukb_vbm":{
  "__set__":true,
  "elements":[
   "junifer"
  ]
 },
 "junifer.data":{
  "__set__":true,
  "elements":[
   "junifer"
  ]
 },
 "junifer.data.coordinates":{
  "__set__":true,
  "elements":[
   "junifer"
  ]
 },
 "junifer.data.masks":{
  "__set__":true,
  "elements":[
   "junifer"
  ]
 },
 "junifer.data.parcellations":{
  "__set__":true,
  "elements":[
   "junifer"
  ]
 },
 "junifer.data.utils":{
  "__set__":true,
  "elements":[
   "junifer"
  ]
 },
 "junifer.datagrabber":{
  "__set__":true,
  "elements":[
   "junifer"
  ]
 },
 "junifer.datagrabber.aomic":{
  "__set__":true,
  "elements":[
   "junifer"
  ]
 },
 "junifer.datagrabber.aomic.id1000":{
  "__set__":true,
  "elements":[
   "junifer"
  ]
 },
 "junifer.datagrabber.aomic.piop1":{
  "__set__":true,
  "elements":[
   "junifer"
  ]
 },
 "junifer.datagrabber.aomic.piop2":{
  "__set__":true,
  "elements":[
   "junifer"
  ]
 },
 "junifer.datagrabber.base":{
  "__set__":true,
  "elements":[
   "junifer"
  ]
 },
 "junifer.datagrabber.datalad_base":{
  "__set__":true,
  "elements":[
   "junifer"
  ]
 },
 "junifer.datagrabber.hcp":{
  "__set__":true,
  "elements":[
   "junifer"
  ]
 },
 "junifer.datagrabber.multiple":{
  "__set__":true,
  "elements":[
   "junifer"
  ]
 },
 "junifer.datagrabber.pattern":{
  "__set__":true,
  "elements":[
   "junifer"
  ]
 },
 "junifer.datagrabber.pattern_datalad":{
  "__set__":true,
  "elements":[
   "junifer"
  ]
 },
 "junifer.datagrabber.utils":{
  "__set__":true,
  "elements":[
   "junifer"
  ]
 },
 "junifer.datareader":{
  "__set__":true,
  "elements":[
   "junifer"
  ]
 },
 "junifer.datareader.default":{
  "__set__":true,
  "elements":[
   "junifer"
  ]
 },
 "junifer.external":{
  "__set__":true,
  "elements":[
   "junifer"
  ]
 },
 "junifer.external.h5io.h5io":{
  "__set__":true,
  "elements":[
   "junifer"
  ]
 },
 "junifer.external.h5io.h5io._h5io":{
  "__set__":true,
  "elements":[
   "junifer"
  ]
 },
 "junifer.external.h5io.h5io._version":{
  "__set__":true,
  "elements":[
   "junifer"
  ]
 },
 "junifer.external.h5io.h5io.chunked_array":{
  "__set__":true,
  "elements":[
   "junifer"
  ]
 },
 "junifer.external.h5io.h5io.chunked_list":{
  "__set__":true,
  "elements":[
   "junifer"
  ]
 },
 "junifer.external.nilearn":{
  "__set__":true,
  "elements":[
   "junifer"
  ]
 },
 "junifer.external.nilearn.junifer_nifti_spheres_masker":{
  "__set__":true,
  "elements":[
   "junifer"
  ]
 },
 "junifer.markers":{
  "__set__":true,
  "elements":[
   "junifer"
  ]
 },
 "junifer.markers.base":{
  "__set__":true,
  "elements":[
   "junifer"
  ]
 },
 "junifer.markers.collection":{
  "__set__":true,
  "elements":[
   "junifer"
  ]
 },
 "junifer.markers.ets_rss":{
  "__set__":true,
  "elements":[
   "junifer"
  ]
 },
 "junifer.markers.falff":{
  "__set__":true,
  "elements":[
   "junifer"
  ]
 },
 "junifer.markers.falff.falff_base":{
  "__set__":true,
  "elements":[
   "junifer"
  ]
 },
 "junifer.markers.falff.falff_estimator":{
  "__set__":true,
  "elements":[
   "junifer"
  ]
 },
 "junifer.markers.falff.falff_parcels":{
  "__set__":true,
  "elements":[
   "junifer"
  ]
 },
 "junifer.markers.falff.falff_spheres":{
  "__set__":true,
  "elements":[
   "junifer"
  ]
 },
 "junifer.markers.functional_connectivity":{
  "__set__":true,
  "elements":[
   "junifer"
  ]
 },
 "junifer.markers.functional_connectivity.crossparcellation_functional_connectivity":{
  "__set__":true,
  "elements":[
   "junifer"
  ]
 },
 "junifer.markers.functional_connectivity.edge_functional_connectivity_parcels":{
  "__set__":true,
  "elements":[
   "junifer"
  ]
 },
 "junifer.markers.functional_connectivity.edge_functional_connectivity_spheres":{
  "__set__":true,
  "elements":[
   "junifer"
  ]
 },
 "junifer.markers.functional_connectivity.functional_connectivity_base":{
  "__set__":true,
  "elements":[
   "junifer"
  ]
 },
 "junifer.markers.functional_connectivity.functional_connectivity_parcels":{
  "__set__":true,
  "elements":[
   "junifer"
  ]
 },
 "junifer.markers.functional_connectivity.functional_connectivity_spheres":{
  "__set__":true,
  "elements":[
   "junifer"
  ]
 },
 "junifer.markers.parcel_aggregation":{
  "__set__":true,
  "elements":[
   "junifer"
  ]
 },
 "junifer.markers.reho":{
  "__set__":true,
  "elements":[
   "junifer"
  ]
 },
 "junifer.markers.reho.reho_base":{
  "__set__":true,
  "elements":[
   "junifer"
  ]
 },
 "junifer.markers.reho.reho_estimator":{
  "__set__":true,
  "elements":[
   "junifer"
  ]
 },
 "junifer.markers.reho.reho_parcels":{
  "__set__":true,
  "elements":[
   "junifer"
  ]
 },
 "junifer.markers.reho.reho_spheres":{
  "__set__":true,
  "elements":[
   "junifer"
  ]
 },
 "junifer.markers.sphere_aggregation":{
  "__set__":true,
  "elements":[
   "junifer"
  ]
 },
 "junifer.markers.temporal_snr":{
  "__set__":true,
  "elements":[
   "junifer"
  ]
 },
 "junifer.markers.temporal_snr.temporal_snr_base":{
  "__set__":true,
  "elements":[
   "junifer"
  ]
 },
 "junifer.markers.temporal_snr.temporal_snr_parcels":{
  "__set__":true,
  "elements":[
   "junifer"
  ]
 },
 "junifer.markers.temporal_snr.temporal_snr_spheres":{
  "__set__":true,
  "elements":[
   "junifer"
  ]
 },
 "junifer.markers.utils":{
  "__set__":true,
  "elements":[
   "junifer"
  ]
 },
 "junifer.pipeline":{
  "__set__":true,
  "elements":[
   "junifer"
  ]
 },
 "junifer.pipeline.pipeline_step_mixin":{
  "__set__":true,
  "elements":[
   "junifer"
  ]
 },
 "junifer.pipeline.registry":{
  "__set__":true,
  "elements":[
   "junifer"
  ]
 },
 "junifer.pipeline.update_meta_mixin":{
  "__set__":true,
  "elements":[
   "junifer"
  ]
 },
 "junifer.pipeline.utils":{
  "__set__":true,
  "elements":[
   "junifer"
  ]
 },
 "junifer.preprocess":{
  "__set__":true,
  "elements":[
   "junifer"
  ]
 },
 "junifer.preprocess.base":{
  "__set__":true,
  "elements":[
   "junifer"
  ]
 },
 "junifer.preprocess.confounds":{
  "__set__":true,
  "elements":[
   "junifer"
  ]
 },
 "junifer.preprocess.confounds.fmriprep_confound_remover":{
  "__set__":true,
  "elements":[
   "junifer"
  ]
 },
 "junifer.stats":{
  "__set__":true,
  "elements":[
   "junifer"
  ]
 },
 "junifer.storage":{
  "__set__":true,
  "elements":[
   "junifer"
  ]
 },
 "junifer.storage.base":{
  "__set__":true,
  "elements":[
   "junifer"
  ]
 },
 "junifer.storage.hdf5":{
  "__set__":true,
  "elements":[
   "junifer"
  ]
 },
 "junifer.storage.pandas_base":{
  "__set__":true,
  "elements":[
   "junifer"
  ]
 },
 "junifer.storage.sqlite":{
  "__set__":true,
  "elements":[
   "junifer"
  ]
 },
 "junifer.storage.utils":{
  "__set__":true,
  "elements":[
   "junifer"
  ]
 },
 "junifer.testing":{
  "__set__":true,
  "elements":[
   "junifer"
  ]
 },
 "junifer.testing.datagrabbers":{
  "__set__":true,
  "elements":[
   "junifer"
  ]
 },
 "junifer.testing.registry":{
  "__set__":true,
  "elements":[
   "junifer"
  ]
 },
 "junifer.testing.utils":{
  "__set__":true,
  "elements":[
   "junifer"
  ]
 },
 "junifer.utils":{
  "__set__":true,
  "elements":[
   "junifer"
  ]
 },
 "junifer.utils.fs":{
  "__set__":true,
  "elements":[
   "junifer"
  ]
 },
 "junifer.utils.logging":{
  "__set__":true,
  "elements":[
   "junifer"
  ]
 }
}